github_snooze_button-0.2.0.dist-info/DESCRIPTION.rst
github_snooze_button-0.2.0.dist-info/METADATA
github_snooze_button-0.2.0.dist-info/RECORD
github_snooze_button-0.2.0.dist-info/WHEEL
github_snooze_button-0.2.0.dist-info/entry_points.txt
github_snooze_button-0.2.0.dist-info/metadata.json
github_snooze_button-0.2.0.dist-info/top_level.txt
snooze/__init__.py
snooze/callbacks.py
snooze/config.py
snooze/constants.py
snooze/deploy_lambda.py
snooze/lambda_handler.py
snooze/repository_listener.py
snooze/snooze.py
snooze/version.py
