Metadata-Version: 2.0
Name: github-snooze-button
Version: 0.2.0
Summary: Snooze button for Github issues
Home-page: https://github.com/tdsmith/github-snooze-button
Author: Tim D. Smith
Author-email: snooze@tds.xyz
License: MIT
Platform: any
Classifier: Development Status :: 4 - Beta
Classifier: Intended Audience :: Developers
Classifier: Topic :: Software Development :: Build Tools
Classifier: License :: OSI Approved :: MIT License
Classifier: Programming Language :: Python :: 2.7
Classifier: Programming Language :: Python :: 3.5
Requires-Dist: boto3
Requires-Dist: requests
